genomix_workflows/__init__.py
genomix_workflows/admin.py
genomix_workflows/apps.py
genomix_workflows/choices.py
genomix_workflows/managers.py
genomix_workflows/models.py
genomix_workflows/services.py
genomix_workflows/signals.py
genomix_workflows/urls.py
genomix_workflows/views.py
genomix_workflows/viewsets.py
genomix_workflows/management/__init__.py
genomix_workflows/management/commands/__init__.py
genomix_workflows/management/commands/create_tasks.py
genomix_workflows/management/commands/create_workflows.py
genomix_workflows/migrations/0001_initial.py
genomix_workflows/migrations/0002_auto_20180516_1649.py
genomix_workflows/migrations/0003_auto_20180518_0647.py
genomix_workflows/migrations/0004_auto_20180601_1216.py
genomix_workflows/migrations/0005_auto_20180604_1104.py
genomix_workflows/migrations/0006_auto_20180605_1323.py
genomix_workflows/migrations/0007_workflow_active.py
genomix_workflows/migrations/0008_task_version.py
genomix_workflows/migrations/0009_auto_20190415_0946.py
genomix_workflows/migrations/0010_add_workflow_type.py
genomix_workflows/migrations/0011_auto_20191008_0908.py
genomix_workflows/migrations/__init__.py
genomix_workflows/static/css/genomix_workflows.css
genomix_workflows/static/css/graph.css
genomix_workflows/static/js/dagre-d3.js
genomix_workflows/static/js/graph.js
genomix_workflows/templates/genomix_workflows/base.html
django_genomix_workflows-0.3.4.dist-info/AUTHORS.rst
django_genomix_workflows-0.3.4.dist-info/LICENSE
django_genomix_workflows-0.3.4.dist-info/METADATA
django_genomix_workflows-0.3.4.dist-info/WHEEL
django_genomix_workflows-0.3.4.dist-info/top_level.txt
django_genomix_workflows-0.3.4.dist-info/RECORD
