Metadata-Version: 2.1
Name: django-genomix-workflows
Version: 0.3.4
Summary: Django App for storing Workflows and Tracking
Home-page: https://github.com/genomics-geek/django-genomix-workflows
Author: Michael A. Gonzalez
Author-email: GonzalezMA@email.chop.edu
License: MIT
Keywords: django-genomix-workflows
Platform: UNKNOWN
Classifier: Development Status :: 4 - Beta
Classifier: Framework :: Django :: 2.0
Classifier: Framework :: Django :: 2.1
Classifier: Framework :: Django :: 2.2
Classifier: Intended Audience :: Developers
Classifier: License :: OSI Approved :: BSD License
Classifier: Natural Language :: English
Classifier: Programming Language :: Python :: 3
Classifier: Programming Language :: Python :: 3.5
Classifier: Programming Language :: Python :: 3.6
Requires-Dist: djangorestframework (==3.10.3)
Requires-Dist: django-filter (==2.2.0)
Requires-Dist: django-genomix (==0.6.10)
Requires-Dist: django-model-utils (==3.2.0)
Requires-Dist: django-reversion (==3.0.4)
Requires-Dist: networkx (==2.3)
Requires-Dist: psycopg2-binary (==2.8.3)
Requires-Dist: pandas (==0.25.1)
